MANIFEST.in
README.md
README.rst
setup.cfg
setup.py
vulk/__init__.py
vulk/baseapp.py
vulk/context.py
vulk/exception.py
vulk/utils.py
vulk/vulkanconstant.py
vulk/vulkanobject.py
vulk.egg-info/PKG-INFO
vulk.egg-info/SOURCES.txt
vulk.egg-info/dependency_links.txt
vulk.egg-info/requires.txt
vulk.egg-info/top_level.txt
vulk/graphic/__init__.py
vulk/graphic/camera.py
vulk/graphic/d2/__init__.py
vulk/graphic/d3/__init__.py
vulk/math/__init__.py
vulk/math/matrix.py
vulk/math/plane.py
vulk/math/vector.py
vulk/tests/__init__.py
vulk/tests/math/__init__.py
vulk/tests/math/test_vector.py