Metadata-Version: 1.1
Name: vulk
Version: 0.2.0
Summary: Vulk: Advanced 3D engine
Home-page: http://github.com/realitix/vulk
Author: realitix
Author-email: realitix@gmail.com
License: Apache 2.0
Platform: UNKNOWN
Classifier: Development Status :: 4 - Beta
Classifier: Intended Audience :: Developers
Classifier: License :: OSI Approved :: Apache Software License
Classifier: Natural Language :: English
Classifier: Programming Language :: Python :: 3.5
Classifier: Programming Language :: Python :: Implementation :: CPython
Classifier: Topic :: Multimedia :: Graphics :: 3D Rendering
